host_replace/__init__.py
host_replace/cli.py
host_replace/host_replace.py
host_replace-0.1.11.dist-info/LICENSE.txt
host_replace-0.1.11.dist-info/METADATA
host_replace-0.1.11.dist-info/WHEEL
host_replace-0.1.11.dist-info/entry_points.txt
host_replace-0.1.11.dist-info/top_level.txt
host_replace-0.1.11.dist-info/RECORD
