Metadata-Version: 2.1
Name: host-replace
Version: 0.1.11
Summary: Replace host and domain names in text under various encoding schemes.
Author-email: Adam Reiser <reiser@defensivecomputing.io>
License: MIT
Project-URL: Homepage, https://github.com/adamreiser/host_replace
Project-URL: Bug Tracker, https://github.com/adamreiser/host_replace/issues
Classifier: Programming Language :: Python :: 3
Classifier: Programming Language :: Python :: 3 :: Only
Classifier: Programming Language :: Python :: 3.9
Classifier: Development Status :: 4 - Beta
Classifier: Intended Audience :: Developers
Classifier: Intended Audience :: System Administrators
Classifier: License :: OSI Approved :: MIT License
Classifier: Operating System :: OS Independent
Classifier: Environment :: Console
Classifier: Topic :: Software Development :: Libraries :: Python Modules
Classifier: Topic :: Text Processing
Classifier: Topic :: Text Processing :: Filters
Classifier: Typing :: Typed
Requires-Python: >=3.9
License-File: LICENSE.txt
Requires-Dist: idna
Requires-Dist: regex
